sqlfun/__init__.py
sqlfun/apps.py
sqlfun/core.py
sqlfun/management/commands/makemigrations.py
sqlfun/migrations/0001_initial.py
sqlfun/migrations/__init__.py
sqlfun/models.py
sqlfun/utils.py
django_sqlfun-0.0.7.dist-info/WHEEL
django_sqlfun-0.0.7.dist-info/METADATA
django_sqlfun-0.0.7.dist-info/licenses/LICENSE
django_sqlfun-0.0.7.dist-info/RECORD
