Metadata-Version: 2.1
Name: django-sqlfun
Version: 0.0.7
Summary: Django app that lets you define custom SQL functions
License: MIT
Keywords: django,database,sql-functions,custom-sql
Author: Radu Suciu
Requires-Python: >=3.10
Classifier: Framework :: Django
Classifier: Framework :: Django :: 4.2
Classifier: Framework :: Django :: 5.0
Classifier: Intended Audience :: Developers
Classifier: License :: OSI Approved :: MIT License
Classifier: Operating System :: OS Independent
Classifier: Programming Language :: Python
Classifier: Programming Language :: Python :: 3 :: Only
Classifier: Programming Language :: Python :: 3.10
Classifier: Programming Language :: Python :: 3.11
Classifier: Programming Language :: Python :: 3.12
Classifier: Topic :: Database
Classifier: Topic :: Software Development :: Libraries
Classifier: Topic :: Software Development :: Libraries :: Python Modules
Requires-Dist: django<6.0,>=4.2
Requires-Dist: sqlparse>=0.4.3
